hazardous/VERSION.txt
hazardous/__init__.py
hazardous/_ipcw.py
hazardous/_survival_boost.py
hazardous/utils.py
hazardous/data/__init__.py
hazardous/data/_competing_weibull.py
hazardous/data/_seer.py
hazardous/data/seer_cancer_cardio_raw_data.txt
hazardous/data/tests/fake_seer_sample.txt
hazardous/data/tests/test_competing_weibull.py
hazardous/data/tests/test_seer.py
hazardous/metrics/__init__.py
hazardous/metrics/_accuracy_in_time.py
hazardous/metrics/_brier_score.py
hazardous/metrics/_concordance_index.py
hazardous/tests/__init__.py
hazardous/tests/test_acc_in_time.py
hazardous/tests/test_cindex.py
hazardous/tests/test_ipcw.py
hazardous/tests/test_metrics.py
hazardous/tests/test_survival_boost.py
hazardous-0.1.0.dist-info/licenses/LICENSE
hazardous-0.1.0.dist-info/WHEEL
hazardous-0.1.0.dist-info/METADATA
hazardous-0.1.0.dist-info/RECORD
