Metadata-Version: 2.4
Name: hazardous
Version: 0.1.0
Summary: Predictive Competing Risks and Survival Analysis.
Author-email: Olivier Grisel <olivier.grisel@ensta.org>, Vincent Maladière <vincent.maladiere@inria.fr>
Requires-Python: >=3.9
Classifier: Programming Language :: Python :: 3
Classifier: License :: OSI Approved :: MIT License
Classifier: Operating System :: OS Independent
License-File: LICENSE
Requires-Dist: numpy
Requires-Dist: scikit-learn
Requires-Dist: tqdm
Requires-Dist: lifelines
Requires-Dist: setuptools
Requires-Dist: pre-commit ; extra == "dev"
Requires-Dist: nox ; extra == "dev"
Requires-Dist: sphinx ; extra == "doc"
Requires-Dist: pydata-sphinx-theme ; extra == "doc"
Requires-Dist: sphinx-gallery ; extra == "doc"
Requires-Dist: sphinx-design ; extra == "doc"
Requires-Dist: sphinx-copybutton ; extra == "doc"
Requires-Dist: matplotlib ; extra == "doc"
Requires-Dist: seaborn ; extra == "doc"
Requires-Dist: pillow ; extra == "doc"
Requires-Dist: numpydoc ; extra == "doc"
Requires-Dist: pycox ; extra == "doc"
Requires-Dist: torch ; extra == "doc"
Requires-Dist: numpy==1.22 ; extra == "oldest-deps"
Requires-Dist: scikit-learn==1.1.3 ; extra == "oldest-deps"
Requires-Dist: pandas==1.5.1 ; extra == "oldest-deps"
Requires-Dist: pytest ; extra == "test"
Requires-Dist: pytest-cov ; extra == "test"
Requires-Dist: pandas ; extra == "test"
Project-URL: Bug Tracker, https://github.com/soda-inria/hazardous/issues
Project-URL: Homepage, https://github.com/soda-inria/hazardous
Provides-Extra: dev
Provides-Extra: doc
Provides-Extra: oldest-deps
Provides-Extra: test
